robi/__init__.py
robi/evaluation.py
robi/evaluation_npy.py
robi/evaluation_torch.py
robi/preselection.py
robi/selection.py
robi/utils.py
robi/utils_preselection.py
robi/utils_selection.py
robi-0.0.16.dist-info/LICENSE
robi-0.0.16.dist-info/METADATA
robi-0.0.16.dist-info/WHEEL
robi-0.0.16.dist-info/top_level.txt
robi-0.0.16.dist-info/RECORD
